{
  "settingsVersion": "1.8.01",
  "makeOfflineCompatible": false,
  "inlineAssets": false,
  "includePluginCSS": "obsidian-code-block-enhancer\nobsidian-git\nfantasy-calendar\ntemplater-obsidian\nobsidian-leaflet-plugin\nobsidian-hider\ntable-editor-obsidian\nobsidian-style-settings\nobsidian-icon-folder\noz-image-plugin\nobsidian-outliner\npane-relief\ndataview\nobsidian-timelines\nobsidian-5e-statblocks\nobsidian-admonition\nobsidian-linter\nquickadd\nobsidian42-brat",
  "includeSvelteCSS": true,
  "titleProperty": "title",
  "customHeadContentPath": "",
  "faviconPath": "",
  "documentWidth": "40em",
  "sidebarWidth": "20em",
  "minOutlineCollapse": 2,
  "startOutlineCollapsed": false,
  "allowFoldingHeadings": true,
  "allowFoldingLists": true,
  "allowResizingSidebars": true,
  "logLevel": "warning",
  "minifyHTML": true,
  "makeNamesWebStyle": true,
  "onlyExportModified": true,
  "deleteOldFiles": true,
  "addThemeToggle": true,
  "addOutline": true,
  "addFileNav": true,
  "addSearchBar": true,
  "addGraphView": true,
  "addTitle": true,
  "addRSSFeed": true,
  "siteURL": "",
  "authorName": "",
  "vaultTitle": "ObsidianDnD.nosync",
  "exportPreset": "website",
  "openAfterExport": false,
  "graphAttractionForce": 1,
  "graphLinkLength": 10,
  "graphRepulsionForce": 150,
  "graphCentralForce": 3,
  "graphEdgePruning": 100,
  "graphMinNodeSize": 3,
  "graphMaxNodeSize": 7,
  "showDefaultTreeIcons": false,
  "emojiStyle": "Native",
  "defaultFileIcon": "lucide//file",
  "defaultFolderIcon": "lucide//folder",
  "defaultMediaIcon": "lucide//file-image",
  "exportPath": "",
  "filesToExport": [
    []
  ],
  "inlineCSS": false,
  "inlineJS": false,
  "inlineImages": true,
  "addDarkModeToggle": true,
  "includeOutline": true,
  "customLineWidth": 0,
  "lastExportPath": "C:/Users/timl/OneDrive - Driessen Groep/Documenten/ObsidianHTML"
}